venice_ai/__init__.py
venice_ai/_async_client.py
venice_ai/_client.py
venice_ai/_client_with_retries.py
venice_ai/_constants.py
venice_ai/_resource.py
venice_ai/costs.py
venice_ai/exceptions.py
venice_ai/resources/__init__.py
venice_ai/resources/api_keys.py
venice_ai/resources/audio.py
venice_ai/resources/billing.py
venice_ai/resources/characters.py
venice_ai/resources/chat/__init__.py
venice_ai/resources/chat/completions.py
venice_ai/resources/embeddings.py
venice_ai/resources/image.py
venice_ai/resources/models.py
venice_ai/streaming.py
venice_ai/types/__init__.py
venice_ai/types/api_keys.py
venice_ai/types/audio.py
venice_ai/types/billing.py
venice_ai/types/characters.py
venice_ai/types/chat.py
venice_ai/types/embeddings.py
venice_ai/types/image.py
venice_ai/types/models.py
venice_ai/utils.py
venice_ai-1.3.0.dist-info/METADATA
venice_ai-1.3.0.dist-info/WHEEL
venice_ai-1.3.0.dist-info/entry_points.txt
venice_ai-1.3.0.dist-info/RECORD
