Metadata-Version: 2.3
Name: venice-ai
Version: 1.3.0
Summary: Python client library for interacting with the Venice.ai API, offering comprehensive access to its features.
License: MIT
Keywords: ai,api-client,generative-ai,llm,machine-learning,ml,sdk,venice,venice-ai
Author: Seth Bang
Author-email: seth@sbang.io
Requires-Python: >=3.11,<4.0
Classifier: Development Status :: 5 - Production/Stable
Classifier: Intended Audience :: Developers
Classifier: License :: OSI Approved :: MIT License
Classifier: Natural Language :: English
Classifier: Operating System :: OS Independent
Classifier: Programming Language :: Python :: 3
Classifier: Programming Language :: Python :: 3.11
Classifier: Programming Language :: Python :: 3.12
Classifier: Programming Language :: Python :: 3.13
Classifier: Topic :: Communications :: Chat
Classifier: Topic :: Multimedia :: Graphics
Classifier: Topic :: Multimedia :: Sound/Audio :: Speech
Classifier: Topic :: Scientific/Engineering :: Artificial Intelligence
Classifier: Topic :: Software Development :: Libraries :: Python Modules
Classifier: Topic :: Text Processing :: General
Classifier: Typing :: Typed
Provides-Extra: tokenizers
Requires-Dist: httpx (>=0.28.0,<0.29.0)
Requires-Dist: httpx-retries (>=0.4.0,<0.5.0)
Requires-Dist: pydantic (>=2.7.0,<3.0.0)
Requires-Dist: tiktoken (>=0.9.0) ; extra == "tokenizers"
Requires-Dist: typing_extensions (>=4.7.0,<5.0.0)
Project-URL: Changelog, https://github.com/sethbang/venice-ai/blob/main/CHANGELOG.md
Project-URL: Documentation, https://venice-ai.readthedocs.io/
Project-URL: Homepage, https://github.com/sethbang/venice-ai
Project-URL: Issue Tracker, https://github.com/sethbang/venice-ai/issues
Project-URL: Repository, https://github.com/sethbang/venice-ai
